{
    "1": {
        "BS Penalty Laps": null,
        "Best Time": "01:42.162",
        "Black Flag Laps": 1,
        "Class": "A",
        "Hash": "u8sTyslZmVmIFvQQ",
        "Laps": 373,
        "Make": "Toyota",
        "Model": "MR2",
        "Number": 85,
        "Team Name": "Dai Mondai II",
        "Year": 1985
    },
    "10": {
        "BS Penalty Laps": null,
        "Best Time": "01:46.568",
        "Black Flag Laps": null,
        "Class": "B",
        "Hash": "9g8kICmqXDyeAS6g",
        "Laps": 333,
        "Make": "Merkur",
        "Model": "XR4Ti",
        "Number": 187,
        "Team Name": "THE Tools",
        "Year": 1987
    },
    "11": {
        "BS Penalty Laps": null,
        "Best Time": "01:53.383",
        "Black Flag Laps": null,
        "Class": "B",
        "Hash": "fkoSVC9JeLCSEc8c",
        "Laps": 333,
        "Make": "Dodge",
        "Model": "Neon",
        "Number": 27,
        "Team Name": "The Cheap Bastards",
        "Year": 1995
    },
    "12": {
        "BS Penalty Laps": null,
        "Best Time": "01:48.554",
        "Black Flag Laps": null,
        "Class": "B",
        "Hash": "fZHEoucpqux4hAXf",
        "Laps": 332,
        "Make": "Chevy",
        "Model": "S10 Lumberhauler",
        "Number": 411,
        "Team Name": "Pickup Trash",
        "Year": 1986
    },
    "13": {
        "BS Penalty Laps": 5,
        "Best Time": "01:49.581",
        "Black Flag Laps": null,
        "Class": "A",
        "Hash": "EkvoJBkkev3ANEJc",
        "Laps": 331,
        "Make": "Dodge",
        "Model": "Neon",
        "Number": 69,
        "Team Name": "Neon Light District",
        "Year": 1996
    },
    "14": {
        "BS Penalty Laps": null,
        "Best Time": "01:51.412",
        "Black Flag Laps": null,
        "Class": "A",
        "Hash": "qlYi8Z4G61cruTVa",
        "Laps": 328,
        "Make": "Toyota",
        "Model": "Corolla FX16",
        "Number": 87,
        "Team Name": "Dai Mondai I",
        "Year": 1987
    },
    "15": {
        "BS Penalty Laps": null,
        "Best Time": "01:53.825",
        "Black Flag Laps": null,
        "Class": "A",
        "Hash": "AuSln2GnQbDRUPJt",
        "Laps": 327,
        "Make": "Honda",
        "Model": "Civic / Camaro",
        "Number": 33,
        "Team Name": "HardDriveRacing2",
        "Year": 2005
    },
    "16": {
        "BS Penalty Laps": null,
        "Best Time": "01:48.903",
        "Black Flag Laps": null,
        "Class": "A",
        "Hash": "e77Sgzu7R0HodEjW",
        "Laps": 326,
        "Make": "Alfa Romeo",
        "Model": "Berlina",
        "Number": 117,
        "Team Name": "Merry Men",
        "Year": 1969
    },
    "17": {
        "BS Penalty Laps": null,
        "Best Time": "01:46.016",
        "Black Flag Laps": null,
        "Class": "A",
        "Hash": "5awhypncqidG7ERy",
        "Laps": 322,
        "Make": "Acura",
        "Model": "Integra",
        "Number": 93,
        "Team Name": "Lucky Monkey Racing",
        "Year": 1993
    },
    "18": {
        "BS Penalty Laps": null,
        "Best Time": "01:50.052",
        "Black Flag Laps": null,
        "Class": "C",
        "Hash": "HkiOLXE6nHuCeFeZ",
        "Laps": 320,
        "Make": "Dodge",
        "Model": "Shadow",
        "Number": 718,
        "Team Name": "Le Shadow",
        "Year": 1993
    },
    "19": {
        "BS Penalty Laps": null,
        "Best Time": "01:47.693",
        "Black Flag Laps": null,
        "Class": "B",
        "Hash": "Ha7x4W83yBK5JsvX",
        "Laps": 318,
        "Make": "Chevy",
        "Model": "Malibu",
        "Number": 350,
        "Team Name": "Ghetto Motorsports",
        "Year": 1978
    },
    "2": {
        "BS Penalty Laps": 1,
        "Best Time": "01:43.984",
        "Black Flag Laps": null,
        "Class": "A",
        "Hash": "vd3b3fMBdWr8Gz0Z",
        "Laps": 367,
        "Make": "Dodge",
        "Model": "Neon",
        "Number": 56,
        "Team Name": "Skid Marks Racing",
        "Year": 1995
    },
    "20": {
        "BS Penalty Laps": null,
        "Best Time": "01:44.333",
        "Black Flag Laps": null,
        "Class": "A",
        "Hash": "MnIQi286bsZEagic",
        "Laps": 317,
        "Make": "Mazda",
        "Model": "RX-7",
        "Number": 99,
        "Team Name": "Team Jager Bombers",
        "Year": 1989
    },
    "21": {
        "BS Penalty Laps": null,
        "Best Time": "01:49.766",
        "Black Flag Laps": null,
        "Class": "A",
        "Hash": "79zVcpE0B3XdLJxR",
        "Laps": 316,
        "Make": "Honda",
        "Model": "Civic",
        "Number": 14,
        "Team Name": "Kamikaze Pilots of Fury",
        "Year": 1989
    },
    "22": {
        "BS Penalty Laps": null,
        "Best Time": "01:55.740",
        "Black Flag Laps": null,
        "Class": "C",
        "Hash": "vf0nh2exv6h8Lopj",
        "Laps": 310,
        "Make": "Geo",
        "Model": "Metro",
        "Number": 53,
        "Team Name": "LemonAid Racing",
        "Year": 1996
    },
    "23": {
        "BS Penalty Laps": null,
        "Best Time": "01:49.648",
        "Black Flag Laps": null,
        "Class": "B",
        "Hash": "sLSkjqbiPqytmqGI",
        "Laps": 304,
        "Make": "VW",
        "Model": "Jetta",
        "Number": 90,
        "Team Name": "Euro Trash",
        "Year": 1990
    },
    "24": {
        "BS Penalty Laps": null,
        "Best Time": "01:54.498",
        "Black Flag Laps": null,
        "Class": "B",
        "Hash": "4JrimBHpersTa85L",
        "Laps": 304,
        "Make": "Volvo",
        "Model": "740",
        "Number": 42,
        "Team Name": "C&H Racing",
        "Year": 1985
    },
    "25": {
        "BS Penalty Laps": 3,
        "Best Time": "01:47.076",
        "Black Flag Laps": null,
        "Class": "A",
        "Hash": "RG8pkRCn2rHMI53Q",
        "Laps": 300,
        "Make": "Toyota",
        "Model": "Supra",
        "Number": 52,
        "Team Name": "Hand Me Down Crap",
        "Year": 1987
    },
    "26": {
        "BS Penalty Laps": 2,
        "Best Time": "01:46.613",
        "Black Flag Laps": null,
        "Class": "A",
        "Hash": "gKvmaPUqiV6kzlYG",
        "Laps": 299,
        "Make": "Honda",
        "Model": "Prelude Si",
        "Number": 13,
        "Team Name": "Hell Kitty Racing",
        "Year": 1988
    },
    "27": {
        "BS Penalty Laps": null,
        "Best Time": "01:51.800",
        "Black Flag Laps": null,
        "Class": "B",
        "Hash": "XTpoanKoNOT3VBC5",
        "Laps": 299,
        "Make": "Buick",
        "Model": "LeSabretooth",
        "Number": 24,
        "Team Name": "Track Pillagerz!",
        "Year": 1999
    },
    "28": {
        "BS Penalty Laps": null,
        "Best Time": "01:51.876",
        "Black Flag Laps": null,
        "Class": "B",
        "Hash": "s5EvHBTbVASwjUOv",
        "Laps": 295,
        "Make": "Honda",
        "Model": "Accord",
        "Number": 12,
        "Team Name": "The Blue Shells",
        "Year": 1989
    },
    "29": {
        "BS Penalty Laps": null,
        "Best Time": "01:44.656",
        "Black Flag Laps": null,
        "Class": "B",
        "Hash": "UZxVfPw7xmrSQCN7",
        "Laps": 294,
        "Make": "Fiat / Bertone",
        "Model": "X1 / 9",
        "Number": 0,
        "Team Name": "Launcha Splatos",
        "Year": 1986
    },
    "3": {
        "BS Penalty Laps": null,
        "Best Time": "01:45.071",
        "Black Flag Laps": null,
        "Class": "A",
        "Hash": "1gBkgNLFcpsCIRIE",
        "Laps": 367,
        "Make": "Volkswagen",
        "Model": "Golf",
        "Number": 991,
        "Team Name": "Team Short Bus",
        "Year": 1995
    },
    "30": {
        "BS Penalty Laps": 2,
        "Best Time": "01:47.994",
        "Black Flag Laps": null,
        "Class": "A",
        "Hash": "0gUAhKhGTDXCFQjD",
        "Laps": 294,
        "Make": "Dodge",
        "Model": "Neon",
        "Number": 797,
        "Team Name": "White Trash Racing",
        "Year": 1996
    },
    "31": {
        "BS Penalty Laps": 2,
        "Best Time": "01:49.070",
        "Black Flag Laps": null,
        "Class": "C",
        "Hash": "LllhMMrhAfOhmP0k",
        "Laps": 294,
        "Make": "Ford",
        "Model": "Fiesta",
        "Number": 79,
        "Team Name": "Dos Limons (Car 2 of 2)",
        "Year": 1978
    },
    "32": {
        "BS Penalty Laps": null,
        "Best Time": "01:49.380",
        "Black Flag Laps": null,
        "Class": "B",
        "Hash": "UvikKWpXaNxd7eih",
        "Laps": 290,
        "Make": "Honda",
        "Model": "CRX",
        "Number": 75,
        "Team Name": "Team Slightly-less-than-credibles",
        "Year": 1991
    },
    "33": {
        "BS Penalty Laps": null,
        "Best Time": "01:52.466",
        "Black Flag Laps": null,
        "Class": "B",
        "Hash": "gFymppzCE6BNapBe",
        "Laps": 287,
        "Make": "Volvo",
        "Model": "245",
        "Number": 86,
        "Team Name": "Little Lebowski Urban Achievers",
        "Year": 1986
    },
    "34": {
        "BS Penalty Laps": null,
        "Best Time": "01:52.751",
        "Black Flag Laps": null,
        "Class": "A",
        "Hash": "yNEE9EYw0ZAiKaVD",
        "Laps": 282,
        "Make": "Nissan",
        "Model": "Sentra XE 1.6L",
        "Number": 10,
        "Team Name": "Dr. Bob's Mobile Dental Clinic",
        "Year": 1994
    },
    "35": {
        "BS Penalty Laps": null,
        "Best Time": "01:49.811",
        "Black Flag Laps": null,
        "Class": "B",
        "Hash": "gJ0L4KTZqfRGGo7I",
        "Laps": 282,
        "Make": "Ford",
        "Model": "Crown Vic V8 Supercar",
        "Number": 707,
        "Team Name": "To Punish and Enslave",
        "Year": 1994
    },
    "36": {
        "BS Penalty Laps": null,
        "Best Time": "01:49.547",
        "Black Flag Laps": null,
        "Class": "A",
        "Hash": "EtLZpOzgihKt152w",
        "Laps": 281,
        "Make": "Mazda",
        "Model": "MX-3",
        "Number": 111,
        "Team Name": "Landshark",
        "Year": 1993
    },
    "37": {
        "BS Penalty Laps": null,
        "Best Time": "01:51.489",
        "Black Flag Laps": null,
        "Class": "B",
        "Hash": "B00oy2h4v2IXqJ91",
        "Laps": 281,
        "Make": "Chevy",
        "Model": "Camaro",
        "Number": 54,
        "Team Name": "Sod Busters",
        "Year": 1992
    },
    "38": {
        "BS Penalty Laps": null,
        "Best Time": "01:42.107",
        "Black Flag Laps": null,
        "Class": "A",
        "Hash": "HKtP2hdpQMcIdrKN",
        "Laps": 275,
        "Make": "Honda",
        "Model": "CRX SI",
        "Number": 61,
        "Team Name": "Clueless Racing",
        "Year": 1989
    },
    "39": {
        "BS Penalty Laps": null,
        "Best Time": "01:43.994",
        "Black Flag Laps": null,
        "Class": "A",
        "Hash": "EvQFcCoKSgbuyigv",
        "Laps": 274,
        "Make": "Lexus",
        "Model": "LS400",
        "Number": 77,
        "Team Name": "Don't Mess With Lexas!",
        "Year": 1991
    },
    "4": {
        "BS Penalty Laps": null,
        "Best Time": "01:45.428",
        "Black Flag Laps": null,
        "Class": "A",
        "Hash": "wjF6WaSrwETMGKY7",
        "Laps": 361,
        "Make": "Plymouth",
        "Model": "Neon",
        "Number": 17,
        "Team Name": "Latch-Key Kids",
        "Year": 1996
    },
    "40": {
        "BS Penalty Laps": null,
        "Best Time": "01:48.525",
        "Black Flag Laps": null,
        "Class": "C",
        "Hash": "bUkgGOeHaPCqJ9Ws",
        "Laps": 270,
        "Make": "Mercury",
        "Model": "Capri",
        "Number": 29,
        "Team Name": "Lemon Squeezers",
        "Year": 1993
    },
    "41": {
        "BS Penalty Laps": null,
        "Best Time": "01:47.850",
        "Black Flag Laps": null,
        "Class": "A",
        "Hash": "GiZMocH4F0GYaQaH",
        "Laps": 268,
        "Make": "Dodge",
        "Model": "Neon",
        "Number": 35,
        "Team Name": "Red Rocket Racing",
        "Year": 1995
    },
    "42": {
        "BS Penalty Laps": null,
        "Best Time": "01:42.661",
        "Black Flag Laps": null,
        "Class": "A",
        "Hash": "xAqV9IKdW4UdkYcd",
        "Laps": 265,
        "Make": "Chevrolet",
        "Model": "Camaro",
        "Number": 36,
        "Team Name": "Save The Ta-Tas Racing",
        "Year": 1984
    },
    "43": {
        "BS Penalty Laps": null,
        "Best Time": "01:47.660",
        "Black Flag Laps": null,
        "Class": "A",
        "Hash": "GTiLl97xmszP41oG",
        "Laps": 261,
        "Make": "Alfa Romeo",
        "Model": "Milano Silver",
        "Number": 110,
        "Team Name": "Iron Oxide Racing",
        "Year": 1987
    },
    "44": {
        "BS Penalty Laps": null,
        "Best Time": "01:59.159",
        "Black Flag Laps": null,
        "Class": "C",
        "Hash": "P9259LlWciia86CH",
        "Laps": 257,
        "Make": "MG",
        "Model": "BGT",
        "Number": 40,
        "Team Name": "Dover Bros Racin",
        "Year": 1970
    },
    "45": {
        "BS Penalty Laps": 1,
        "Best Time": "01:44.391",
        "Black Flag Laps": null,
        "Class": "C",
        "Hash": "tVXP7W1gD9g1lPLV",
        "Laps": 252,
        "Make": "Ford",
        "Model": "Fiesta",
        "Number": 78,
        "Team Name": "Dos Limons (Car 1 of 2)",
        "Year": 1979
    },
    "46": {
        "BS Penalty Laps": null,
        "Best Time": "01:52.754",
        "Black Flag Laps": null,
        "Class": "B",
        "Hash": "aNUk5Z9OU3GXiiK2",
        "Laps": 244,
        "Make": "Honda",
        "Model": "CRX",
        "Number": 4,
        "Team Name": "Kamikaze pilots of fury 2",
        "Year": 1990
    },
    "47": {
        "BS Penalty Laps": null,
        "Best Time": "01:54.931",
        "Black Flag Laps": null,
        "Class": "B",
        "Hash": "Frh0UPa2QIjusg0x",
        "Laps": 227,
        "Make": "Nissan",
        "Model": "200sx 1.6",
        "Number": 46,
        "Team Name": "Wisconsin Crap Racing",
        "Year": 1998
    },
    "48": {
        "BS Penalty Laps": null,
        "Best Time": "01:47.160",
        "Black Flag Laps": null,
        "Class": "A",
        "Hash": "6sDeHCxqEPyUv9Zi",
        "Laps": 224,
        "Make": "bmw",
        "Model": "325is",
        "Number": 71,
        "Team Name": "All Whammies",
        "Year": 1987
    },
    "49": {
        "BS Penalty Laps": 1,
        "Best Time": "01:44.872",
        "Black Flag Laps": null,
        "Class": "A",
        "Hash": "Cv5zmoqVp3n5bSlg",
        "Laps": 194,
        "Make": "Alfa Romeo",
        "Model": "GTV6",
        "Number": 908,
        "Team Name": "Single Malt Racing",
        "Year": 1986
    },
    "5": {
        "BS Penalty Laps": null,
        "Best Time": "01:46.278",
        "Black Flag Laps": null,
        "Class": "A",
        "Hash": "4zH5WFogub5RfqCS",
        "Laps": 354,
        "Make": "Toyota",
        "Model": "Celica ST",
        "Number": 11,
        "Team Name": "Team Reynolds Style",
        "Year": 1995
    },
    "50": {
        "BS Penalty Laps": null,
        "Best Time": "01:48.875",
        "Black Flag Laps": null,
        "Class": "A",
        "Hash": "KXQyRwCvEZKIFdVg",
        "Laps": 194,
        "Make": "Dodge",
        "Model": "Neon",
        "Number": 64,
        "Team Name": "Team Lebowski",
        "Year": 1996
    },
    "51": {
        "BS Penalty Laps": 13,
        "Best Time": "01:54.953",
        "Black Flag Laps": null,
        "Class": "A",
        "Hash": "9HNCiFaSy32Olxla",
        "Laps": 192,
        "Make": "Mazda",
        "Model": "rx7",
        "Number": 47,
        "Team Name": "Bad lucky touch",
        "Year": 1984
    },
    "52": {
        "BS Penalty Laps": null,
        "Best Time": "01:52.485",
        "Black Flag Laps": null,
        "Class": "B",
        "Hash": "2v982Ol7X3l0q8U0",
        "Laps": 190,
        "Make": "Chevrolet",
        "Model": "Camaro Iroc",
        "Number": 3,
        "Team Name": "HardDriveRacing",
        "Year": 1985
    },
    "53": {
        "BS Penalty Laps": null,
        "Best Time": "01:53.680",
        "Black Flag Laps": null,
        "Class": "A",
        "Hash": "OriEHIwvS1LXwMEZ",
        "Laps": 188,
        "Make": "Mazda",
        "Model": "rx7",
        "Number": 37,
        "Team Name": "The Minty Pylons",
        "Year": 1988
    },
    "54": {
        "BS Penalty Laps": 21,
        "Best Time": "01:45.443",
        "Black Flag Laps": null,
        "Class": "B",
        "Hash": "NYgRJCJQYvXF85Mn",
        "Laps": 184,
        "Make": "Lincoln",
        "Model": "Mark VII",
        "Number": 43,
        "Team Name": "Bison Bandits",
        "Year": 1991
    },
    "55": {
        "BS Penalty Laps": 1,
        "Best Time": "01:48.398",
        "Black Flag Laps": null,
        "Class": "A",
        "Hash": "jFbBXgbF2rX52NAw",
        "Laps": 173,
        "Make": "BMW",
        "Model": "325es",
        "Number": 68,
        "Team Name": "Sergeant Shitbox",
        "Year": 1986
    },
    "56": {
        "BS Penalty Laps": null,
        "Best Time": "01:59.750",
        "Black Flag Laps": null,
        "Class": "B",
        "Hash": "NG30XJC9cbKG5wml",
        "Laps": 148,
        "Make": "Ford",
        "Model": "Escort",
        "Number": 101,
        "Team Name": "Byte Marks Racing",
        "Year": 1992
    },
    "57": {
        "BS Penalty Laps": null,
        "Best Time": "01:50.266",
        "Black Flag Laps": null,
        "Class": "A",
        "Hash": "DgBKJwiicCeqYapI",
        "Laps": 144,
        "Make": "BMW",
        "Model": "325E",
        "Number": 100,
        "Team Name": "Swiss Racing",
        "Year": 1986
    },
    "58": {
        "BS Penalty Laps": null,
        "Best Time": "01:57.809",
        "Black Flag Laps": null,
        "Class": "B",
        "Hash": "5PPdSsetzPhSgABr",
        "Laps": 125,
        "Make": "Ford",
        "Model": "Thunderbird",
        "Number": 70,
        "Team Name": "Captain Morgan's Rum Runners",
        "Year": 1991
    },
    "59": {
        "BS Penalty Laps": null,
        "Best Time": "01:56.411",
        "Black Flag Laps": null,
        "Class": "A",
        "Hash": "uatGkvUiheFBWtBg",
        "Laps": 111,
        "Make": "Honda",
        "Model": "Civic",
        "Number": 8,
        "Team Name": "Civic Disorder",
        "Year": 1994
    },
    "6": {
        "BS Penalty Laps": null,
        "Best Time": "01:55.951",
        "Black Flag Laps": null,
        "Class": "B",
        "Hash": "7AkX6mBqTkdCQsCa",
        "Laps": 352,
        "Make": "Volkswagen",
        "Model": "Quantum Syncro Wagon",
        "Number": 871,
        "Team Name": "Chicken and Waffles",
        "Year": 1987
    },
    "60": {
        "BS Penalty Laps": null,
        "Best Time": "02:05.520",
        "Black Flag Laps": null,
        "Class": "C",
        "Hash": "7ZpilXZTYS1PITX1",
        "Laps": 31,
        "Make": "Pontiac",
        "Model": "Fiero",
        "Number": 200,
        "Team Name": "Double Jeopardy",
        "Year": 1987
    },
    "61": {
        "BS Penalty Laps": null,
        "Best Time": "02:13.793",
        "Black Flag Laps": null,
        "Class": "C",
        "Hash": "HGexXvNzGMVyrbHx",
        "Laps": 30,
        "Make": "Toyota",
        "Model": "Celica",
        "Number": 55,
        "Team Name": "AutoBACS",
        "Year": 1973
    },
    "62": {
        "BS Penalty Laps": null,
        "Best Time": "03:20.078",
        "Black Flag Laps": null,
        "Class": "C",
        "Hash": "ZmY4tawFNutuhdXk",
        "Laps": 9,
        "Make": "Chevy",
        "Model": "Chevette",
        "Number": 2,
        "Team Name": "Zero Budget Racing",
        "Year": 1984
    },
    "63": {
        "BS Penalty Laps": null,
        "Best Time": "02:20.024",
        "Black Flag Laps": null,
        "Class": "B",
        "Hash": "85HkGqtnPMD1Pc60",
        "Laps": 5,
        "Make": "Chevy",
        "Model": "DeCon Monza!!#1013",
        "Number": 113,
        "Team Name": "The Usual Suspects",
        "Year": 1976
    },
    "64": {
        "BS Penalty Laps": null,
        "Best Time": null,
        "Black Flag Laps": null,
        "Class": "C",
        "Hash": "dJ6xz5xmryLjrd4a",
        "Laps": 1,
        "Make": "Toyota",
        "Model": "MR2",
        "Number": 97,
        "Team Name": "Crushed Red Pepper",
        "Year": 1993
    },
    "7": {
        "BS Penalty Laps": null,
        "Best Time": "01:41.618",
        "Black Flag Laps": null,
        "Class": "A",
        "Hash": "rVGd1jOfpQ7MzBxB",
        "Laps": 350,
        "Make": "BMW",
        "Model": "Crappy E30",
        "Number": 25,
        "Team Name": "Bucksnort Racing",
        "Year": 1987
    },
    "8": {
        "BS Penalty Laps": null,
        "Best Time": "01:48.807",
        "Black Flag Laps": null,
        "Class": "B",
        "Hash": "r1iiisRaRfWi5B81",
        "Laps": 348,
        "Make": "Honda",
        "Model": "Civic",
        "Number": 48,
        "Team Name": "Free Candy Racing",
        "Year": 1989
    },
    "9": {
        "BS Penalty Laps": 1,
        "Best Time": "01:46.260",
        "Black Flag Laps": null,
        "Class": "A",
        "Hash": "fPobOjiVdihKjEra",
        "Laps": 338,
        "Make": "Acura",
        "Model": "Integra",
        "Number": 28,
        "Team Name": "Team Non Sequitur",
        "Year": 1992
    },
    "Date": {
        "Day": 16,
        "Month": 4,
        "Year": 2011
    },
    "Name": "Campaign to Prevent Gingervitis"
}